setup.py
automsg/__init__.py
automsg/automsg.py
automsg.egg-info/PKG-INFO
automsg.egg-info/SOURCES.txt
automsg.egg-info/dependency_links.txt
automsg.egg-info/top_level.txt